odoo10_addon_shopinvader_product_template_multi_link-10.0.1.0.1-nspkg.pth
odoo/addons/shopinvader_product_template_multi_link/README.rst
odoo/addons/shopinvader_product_template_multi_link/__init__.py
odoo/addons/shopinvader_product_template_multi_link/__manifest__.py
odoo/addons/shopinvader_product_template_multi_link/data/ir_exports_line.xml
odoo/addons/shopinvader_product_template_multi_link/models/__init__.py
odoo/addons/shopinvader_product_template_multi_link/models/shopinvader_product.py
odoo/addons/shopinvader_product_template_multi_link/tests/__init__.py
odoo/addons/shopinvader_product_template_multi_link/tests/test_product.py
odoo10_addon_shopinvader_product_template_multi_link-10.0.1.0.1.dist-info/METADATA
odoo10_addon_shopinvader_product_template_multi_link-10.0.1.0.1.dist-info/WHEEL
odoo10_addon_shopinvader_product_template_multi_link-10.0.1.0.1.dist-info/namespace_packages.txt
odoo10_addon_shopinvader_product_template_multi_link-10.0.1.0.1.dist-info/top_level.txt
odoo10_addon_shopinvader_product_template_multi_link-10.0.1.0.1.dist-info/RECORD
