Metadata-Version: 2.1
Name: odoo10-addon-shopinvader-product-template-multi-link
Version: 10.0.1.0.1
Summary: Shopinvader Product Link
Home-page: https://akretion.com
Author: Akretion,GRAP
License: AGPL-3
Platform: UNKNOWN
Classifier: Programming Language :: Python
Classifier: Framework :: Odoo
Classifier: License :: OSI Approved :: GNU Affero General Public License v3
Requires-Python: ~=2.7
Requires-Dist: odoo10-addon-product-template-multi-link
Requires-Dist: odoo10-addon-shopinvader
Requires-Dist: odoo (<10.1dev,>=10.0)
